{
  "event": {
    "title": "Golden Wings",
    "subtitle": "A 50-Year Journey Through Aviation History",
    "date": "October 26, 2025",
    "timePST": "4:30 PM",
    "timeCST": "6:30 PM",
    "timeEST": "7:30 PM",
    "venue": "747 First Class Lounge",
    "duration": "25 minutes",
    "description": "Golden Wings chronicles the remarkable career of Robyn Stewart, an American Airlines flight attendant whose 50+ years in the skies witnessed the transformation of commercial aviation."
  },
  "video": {
    "enabled": true,
    "overlayOpacity": 50,
    "hideOnMobile": false
  },
  "form": {
    "webhookUrl": "https://script.google.com/macros/s/AKfycbxnU3k4duWhFRaMPnUVyp7NaGxG6qPN2Py43eNwCBZz8S0DN5xcMLgUdMAMb7iQ-ewQsg/exec",
    "confirmationUrl": "/confirmation"
  },
  "api": {
    "baseUrl": "https://golden-wings-backend.ondigitalocean.app"
  },
  "contact": {
    "email": "info@golden-wings-robyn.com",
    "website": "https://gwingz.com"
  },
  "theme": {
    "defaultStyle": "soaring-classic",
    "keyMessage": "A 50-Year Journey Through Aviation",
    "headlineAccent": "Join us for an exclusive screening",
    "featureCallouts": [
      "Celebrating 50+ years of aviation excellence",
      "An intimate look at the evolution of air travel",
      "Stories of dedication and service above the clouds"
    ],
    "mobileHighlights": [],
    "palette": {
      "soaring-classic": {
        "panel-backdrop": "rgba(15, 23, 42, 0.45)",
        "panel-border": "rgba(255, 255, 255, 0.08)"
      },
      "twilight-runway": {
        "panel-backdrop": "rgba(15, 23, 42, 0.6)",
        "panel-border": "rgba(147, 197, 253, 0.22)"
      },
      "sunrise-cabin": {
        "panel-backdrop": "rgba(124, 45, 18, 0.45)",
        "panel-border": "rgba(249, 115, 22, 0.25)"
      }
    }
  },
  "meta": {
    "lastUpdated": "2025-10-20T00:00:00Z",
    "version": "1.0.0"
  }
}
